README.rst
setup.cfg
setup.py
sspyrs2/__init__.py
sspyrs2.egg-info/PKG-INFO
sspyrs2.egg-info/SOURCES.txt
sspyrs2.egg-info/dependency_links.txt
sspyrs2.egg-info/not-zip-safe
sspyrs2.egg-info/requires.txt
sspyrs2.egg-info/top_level.txt