Metadata-Version: 1.0
Name: sspyrs2
Version: 1.0.1
Summary: Alternative version of sspyrs that is a lightweight interface for SSRS reports to python.
Home-page: https://pypi.python.org/pypi/sspyrs2
Author: Alex Sazo
Author-email: alexsazo@outlook.com
License: MIT
Keywords: ssrs report reporting sql
Platform: UNKNOWN
